README.md
setup.py
exif_utils/__init__.py
exif_utils/__main__.py
exif_utils/date_classifier.py
exif_utils/utils.py
exif_utils.egg-info/PKG-INFO
exif_utils.egg-info/SOURCES.txt
exif_utils.egg-info/dependency_links.txt
exif_utils.egg-info/entry_points.txt
exif_utils.egg-info/not-zip-safe
exif_utils.egg-info/requires.txt
exif_utils.egg-info/top_level.txt